stroke_lifetime/__init__.py
stroke_lifetime/fixed_params.py
stroke_lifetime/main_calculations.py
stroke_lifetime/models.py
stroke_lifetime-3.0.2.dist-info/LICENSE
stroke_lifetime-3.0.2.dist-info/METADATA
stroke_lifetime-3.0.2.dist-info/WHEEL
stroke_lifetime-3.0.2.dist-info/top_level.txt
stroke_lifetime-3.0.2.dist-info/RECORD
