Metadata-Version: 2.1
Name: stroke-lifetime
Version: 3.0.2
Summary: Stroke lifetime: health economics calculations for lifetime after stroke.
Home-page: https://github.com/stroke-modelling/stroke-lifetime
Author: Anna Laws
Author-email: a.laws2@exeter.ac.uk
License: MIT License (MIT)
Platform: UNKNOWN
Classifier: Programming Language :: Python :: 3.8
Classifier: Programming Language :: Python :: 3.9
Classifier: Programming Language :: Python :: 3.10
Classifier: Programming Language :: Python :: 3.11
Classifier: License :: OSI Approved :: MIT License
Classifier: Operating System :: OS Independent
Requires-Python: >=3.7.17
License-File: LICENSE
Requires-Dist: numpy
